easyauth/__init__.py
easyauth/admin_urls.py
easyauth/apps.py
easyauth/authentication.py
easyauth/conf.py
easyauth/make_project.py
easyauth/middleware.py
easyauth/models.py
easyauth/pagination.py
easyauth/permissions.py
easyauth/serializers.py
easyauth/urls.py
easyauth/views.py
easyauth/locale/zh_hans/LC_MESSAGES/django.mo
easyauth/locale/zh_hans/LC_MESSAGES/django.po
easyauth-0.1.3.data/data/requirements.txt
easyauth-0.1.3.data/data/test-requirements.txt
easyauth-0.1.3.data/data/project_skeleton/.gitignore
easyauth-0.1.3.data/data/project_skeleton/manage.py
easyauth-0.1.3.data/data/project_skeleton/requirements.txt
easyauth-0.1.3.data/data/project_skeleton/test/__init__.py
easyauth-0.1.3.data/data/project_skeleton/test/apps.py
easyauth-0.1.3.data/data/project_skeleton/test/models.py
easyauth-0.1.3.data/data/project_skeleton/test/urls.py
easyauth-0.1.3.data/data/project_skeleton/test/wsgi.py
easyauth-0.1.3.data/data/project_skeleton/test/settings/__init__.py
easyauth-0.1.3.data/data/project_skeleton/test/settings/__init__.pyc
easyauth-0.1.3.data/data/project_skeleton/test/settings/local.py
easyauth-0.1.3.data/data/project_skeleton/test/settings/local.pyc
easyauth-0.1.3.data/data/project_skeleton/test/settings/production.py
easyauth-0.1.3.data/data/project_skeleton/test/settings/production.pyc
easyauth-0.1.3.data/data/project_skeleton/vue-ui/.babelrc
easyauth-0.1.3.data/data/project_skeleton/vue-ui/.editorconfig
easyauth-0.1.3.data/data/project_skeleton/vue-ui/.gitignore
easyauth-0.1.3.data/data/project_skeleton/vue-ui/.postcssrc.js
easyauth-0.1.3.data/data/project_skeleton/vue-ui/README.md
easyauth-0.1.3.data/data/project_skeleton/vue-ui/index.html
easyauth-0.1.3.data/data/project_skeleton/vue-ui/package-lock.json
easyauth-0.1.3.data/data/project_skeleton/vue-ui/package.json
easyauth-0.1.3.data/data/project_skeleton/vue-ui/build/build.js
easyauth-0.1.3.data/data/project_skeleton/vue-ui/build/check-versions.js
easyauth-0.1.3.dist-info/METADATA
easyauth-0.1.3.dist-info/RECORD
easyauth-0.1.3.dist-info/WHEEL
easyauth-0.1.3.dist-info/entry_points.txt
easyauth-0.1.3.dist-info/top_level.txt
