Metadata-Version: 2.1
Name: easyauth
Version: 0.1.3
Summary: A toolkit to set up web application with authentication and authorization functionalities based on Django.
Home-page: https://github.com/qingfeng0820/easyauth
Author: Sherman Liu
Author-email: qingfeng0820@sina.com
Maintainer: Sherman Liu
Maintainer-email: qingfeng0820@sina.com
License: BSD
Keywords: Authentication based on Django,Authorization based on Django,Python web application Auth
Platform: all
Classifier: Programming Language :: Python
Classifier: Programming Language :: Python :: 2.7
Classifier: Natural Language :: English
Classifier: Intended Audience :: Developers
Classifier: Operating System :: OS Independent
Classifier: Development Status :: 4 - Beta
Classifier: Topic :: Utilities
Classifier: License :: OSI Approved :: BSD License
Requires-Dist: django (==1.9)
Requires-Dist: djangorestframework (==3.7)
Requires-Dist: django-cors-headers
Requires-Dist: django-filter (==1.1.0)
